README.rst
setup.cfg
setup.py
freeboxclient/__init__.py
freeboxclient/api.py
freeboxclient/client.py
freeboxclient/common.py
freeboxclient/config.py
freeboxclient/freeboxos.py
freeboxclient/simple.py
freeboxclient/tests/__init__.py
freeboxclient/tests/commons.py
freeboxclient/tests/test_api_auth.py
freeboxclient/tests/test_api_calls.py
freeboxclient/tests/test_api_version.py
freeboxclient/tests/test_api_wifi.py
freeboxclient/tests/test_configuration.py
python_freeboxclient.egg-info/PKG-INFO
python_freeboxclient.egg-info/SOURCES.txt
python_freeboxclient.egg-info/dependency_links.txt
python_freeboxclient.egg-info/entry_points.txt
python_freeboxclient.egg-info/namespace_packages.txt
python_freeboxclient.egg-info/not-zip-safe
python_freeboxclient.egg-info/requires.txt
python_freeboxclient.egg-info/top_level.txt