Metadata-Version: 1.1
Name: python-freeboxclient
Version: 0.1.0
Summary: A client for the FreeboxOS.
Home-page: https://github.com/nlamirault/python-freeboxclient
Author: Nicolas Lamirault
Author-email: nicolas.lamirault@gmail.com
License: UNKNOWN
Download-URL: https://github.com/nlamirault/python-freeboxclient/tarball/master
Platform: Any
Classifier: Development Status :: 3 - Alpha
Classifier: License :: OSI Approved :: Apache Software License
Classifier: Programming Language :: Python
Classifier: Programming Language :: Python :: 2
Classifier: Programming Language :: Python :: 2.7
Classifier: Programming Language :: Python :: 3
Classifier: Programming Language :: Python :: 3.2
Classifier: Intended Audience :: Developers
Classifier: Environment :: Console
